textobfuscator/__init__.py
textobfuscator/auxiliary/__init__.py
textobfuscator/auxiliary/config.py
textobfuscator/auxiliary/replace_maps.py
textobfuscator/obfuscator.py
textobfuscator/processor/__init__.py
textobfuscator/processor/construct.py
textobfuscator/processor/format.py
textobfuscator/processor/replace.py
textobfuscator/processor/word_break.py
textobfuscator/utils.py
textobfuscator-0.1.3.dist-info/LICENSE
textobfuscator-0.1.3.dist-info/WHEEL
textobfuscator-0.1.3.dist-info/METADATA
textobfuscator-0.1.3.dist-info/RECORD
