Metadata-Version: 2.1
Name: textobfuscator
Version: 0.1.3
Summary: Text obfuscator.
Home-page: https://github.com/luxiaba/TextObfuscator
License: MIT
Keywords: text,obfuscator,obfuscate
Author: fishermanadg
Author-email: fishermanadg@gmail.com
Requires-Python: >=3.8.7,<4.0.0
Classifier: Development Status :: 5 - Production/Stable
Classifier: Intended Audience :: Developers
Classifier: License :: OSI Approved :: MIT License
Classifier: Operating System :: MacOS
Classifier: Operating System :: POSIX
Classifier: Operating System :: POSIX :: Linux
Classifier: Programming Language :: Python
Classifier: Programming Language :: Python :: 3
Classifier: Programming Language :: Python :: 3.10
Classifier: Programming Language :: Python :: 3.8
Classifier: Programming Language :: Python :: 3.9
Classifier: Programming Language :: Python :: Implementation :: CPython
Classifier: Programming Language :: Python :: Implementation :: PyPy
Classifier: Topic :: Software Development :: Libraries
Classifier: Topic :: Software Development :: Libraries :: Python Modules
Classifier: Topic :: Utilities
Project-URL: Repository, https://github.com/luxiaba/TextObfuscator.git
